[{"0":0,"-1":0,"-2":2,"-3":1,"-4":1,"-5":0,"-6":0,"-7":0,"name":"Alex","today":0,"total":629,"ordinal":"0th","uniqueDays":361,"last_coffee":"2021-07-21T03:16:55.000Z","dailyAverage":2},{"0":1,"-1":0,"-2":0,"-3":1,"-4":0,"-5":0,"-6":0,"-7":0,"name":"Maricel","today":1,"total":459,"ordinal":"1st","uniqueDays":427,"last_coffee":"2021-07-23T01:51:43.000Z","dailyAverage":2},{"0":0,"-1":0,"-2":0,"-3":0,"-4":0,"-5":0,"-6":0,"-7":2,"name":"Reece","today":0,"total":739,"ordinal":"0th","uniqueDays":386,"last_coffee":"2021-07-16T05:43:44.000Z","dailyAverage":2},{"0":1,"-1":0,"-2":1,"-3":1,"-4":1,"-5":0,"-6":0,"-7":0,"name":"Darren","today":1,"total":160,"ordinal":"1st","uniqueDays":138,"last_coffee":"2021-07-23T01:12:23.000Z","dailyAverage":2},{"0":0,"-1":1,"-2":0,"-3":1,"-4":0,"-5":0,"-6":0,"-7":0,"name":"Owen","today":0,"total":219,"ordinal":"0th","uniqueDays":163,"last_coffee":"2021-07-22T06:34:58.000Z","dailyAverage":2},{"0":1,"-1":1,"-2":1,"-3":1,"-4":1,"-5":0,"-6":0,"-7":0,"name":"Jamie","today":1,"total":1421,"ordinal":"1st","uniqueDays":834,"last_coffee":"2021-07-23T01:01:57.000Z","dailyAverage":2},{"0":2,"-1":1,"-2":2,"-3":2,"-4":2,"-5":0,"-6":0,"-7":2,"name":"Natalie","today":2,"total":1224,"ordinal":"2nd","uniqueDays":602,"last_coffee":"2021-07-23T02:23:27.000Z","dailyAverage":3},{"0":0,"-1":1,"-2":2,"-3":0,"-4":1,"-5":0,"-6":0,"-7":2,"name":"John","today":0,"total":1393,"ordinal":"0th","uniqueDays":692,"last_coffee":"2021-07-22T04:43:42.000Z","dailyAverage":3},{"0":0,"-1":1,"-2":0,"-3":0,"-4":0,"-5":0,"-6":0,"-7":1,"name":"Aj","today":0,"total":201,"ordinal":"0th","uniqueDays":187,"last_coffee":"2021-07-22T04:04:00.000Z","dailyAverage":2},{"0":0,"-1":0,"-2":0,"-3":0,"-4":0,"-5":0,"-6":0,"-7":0,"name":"Lan","today":0,"total":87,"ordinal":"0th","uniqueDays":70,"last_coffee":"2020-08-31T22:36:49.000Z","dailyAverage":2},{"0":0,"-1":0,"-2":0,"-3":0,"-4":0,"-5":0,"-6":0,"-7":0,"name":"Mac","today":0,"total":243,"ordinal":"0th","uniqueDays":225,"last_coffee":"2021-06-17T06:54:24.000Z","dailyAverage":2},{"0":0,"-1":0,"-2":0,"-3":0,"-4":0,"-5":0,"-6":0,"-7":0,"name":"Yong","today":0,"total":51,"ordinal":"0th","uniqueDays":32,"last_coffee":"2020-03-06T04:33:19.000Z","dailyAverage":2},{"0":0,"-1":0,"-2":0,"-3":0,"-4":0,"-5":0,"-6":0,"-7":0,"name":"Corey","today":0,"total":5,"ordinal":"0th","uniqueDays":2,"last_coffee":"2019-11-25T21:12:31.000Z","dailyAverage":3},{"0":0,"-1":2,"-2":2,"-3":0,"-4":1,"-5":0,"-6":0,"-7":2,"name":"Michelle","today":0,"total":247,"ordinal":"0th","uniqueDays":187,"last_coffee":"2021-07-22T14:09:37.000Z","dailyAverage":2},{"0":0,"-1":0,"-2":0,"-3":0,"-4":0,"-5":0,"-6":0,"-7":0,"name":"Corey","today":0,"total":1,"ordinal":null,"uniqueDays":null,"last_coffee":"2021-06-29T01:25:30.000Z","dailyAverage":null}]