[{"name":"Alex","today":1,"total":465,"ordinal":"1st","uniqueDays":268,"last_coffee":"2020-07-07T02:51:42.000Z","dailyAverage":2},{"name":"Maricel","today":1,"total":300,"ordinal":"1st","uniqueDays":284,"last_coffee":"2020-07-07T00:57:18.000Z","dailyAverage":2},{"name":"Reece","today":1,"total":642,"ordinal":"1st","uniqueDays":337,"last_coffee":"2020-07-07T01:14:20.000Z","dailyAverage":2},{"name":"Darren","today":0,"total":46,"ordinal":"0th","uniqueDays":32,"last_coffee":"2020-06-03T03:45:11.000Z","dailyAverage":2},{"name":"Owen","today":1,"total":126,"ordinal":"1st","uniqueDays":88,"last_coffee":"2020-07-07T00:47:18.000Z","dailyAverage":2},{"name":"Jamie","today":0,"total":1115,"ordinal":"0th","uniqueDays":618,"last_coffee":"2020-07-03T01:31:50.000Z","dailyAverage":2},{"name":"Natalie","today":3,"total":744,"ordinal":"3rd","uniqueDays":388,"last_coffee":"2020-07-07T03:59:03.000Z","dailyAverage":2},{"name":"John","today":1,"total":1217,"ordinal":"1st","uniqueDays":588,"last_coffee":"2020-07-07T01:08:46.000Z","dailyAverage":3},{"name":"Aj","today":1,"total":89,"ordinal":"1st","uniqueDays":82,"last_coffee":"2020-07-07T02:52:01.000Z","dailyAverage":2},{"name":"Lan","today":1,"total":66,"ordinal":"1st","uniqueDays":53,"last_coffee":"2020-07-07T01:04:28.000Z","dailyAverage":2},{"name":"Mac","today":1,"total":154,"ordinal":"1st","uniqueDays":141,"last_coffee":"2020-07-07T00:43:00.000Z","dailyAverage":2},{"name":"Yong","today":0,"total":51,"ordinal":"0th","uniqueDays":32,"last_coffee":"2020-03-06T04:33:19.000Z","dailyAverage":2},{"name":"Corey","today":0,"total":5,"ordinal":"0th","uniqueDays":2,"last_coffee":"2019-11-25T21:12:31.000Z","dailyAverage":3},{"name":"Michelle","today":0,"total":19,"ordinal":"0th","uniqueDays":12,"last_coffee":"2020-07-06T07:26:42.000Z","dailyAverage":2}]